Home Alarm System.srcs/sources_1/new/seven_segment_decoder.v
//////////////////////////////////////////////////////////////////////////////////
// This module is active low seven segment decoder
// with the aim to display the input number to
// seven segment display of the FPGA board.
//////////////////////////////////////////////////////////////////////////////////
`timescale 1s / 1ms
module seven_segment_decoder(in,out);

input [3:0]  in;
output reg [6:0]  out;

always @ (in)
case(in)
    4'b0000 : out=7'b1000000; //0
    4'b0001 : out=7'b1111001; //1
    4'b0010 : out=7'b0100100; //2
    4'b0011 : out=7'b0110000; //3
    4'b0100 : out=7'b0011001; //4
    4'b0101 : out=7'b0010010; //5
    4'b0110 : out=7'b0000010; //6
    4'b0111 : out=7'b1111000; //7
    4'b1000 : out=7'b0000000; //8
    4'b1001 : out=7'b0010000; //9
    4'b1010 : out=7'b0001000; //A
    4'b1011 : out=7'b0000011; //B
    4'b1100 : out=7'b1000110; //C
    4'b1101 : out=7'b0100001; //D
    4'b1110 : out=7'b0000110; //E
    4'b1111 : out=7'b0001110; //F
    default : out=7'b1111111; //all off
endcase        

endmodule

Home Alarm System.srcs/sources_1/new/seven_segment_driver.v
//////////////////////////////////////////////////////////////////////////////////
// There are 4 seven segment display on our FPGA, inorder to select the
// correct display for our output, we need a module that can  
// assign the corresponsing output to the display we need.
//////////////////////////////////////////////////////////////////////////////////
`timescale 1s / 1ms
module seven_segment_driver(clk,clr,in1,in2,in3,in4,seg,an);

input clk, clr;
input [3:0] in1, in2, in3, in4;
output reg [6:0] seg;
output reg [3:0] an;

wire [6:0] seg1, seg2, seg3, seg4;
  reg [12:0] segclk=0;

localparam LEFT = 2'b00, MIDLEFT = 2'b01, MIDRIGHT = 2'b10, RIGHT = 2'b11;
reg [1:0] state=LEFT;

//instantiating seven_segment_decoder module for 4 displays
seven_segment_decoder disp1(in1,seg1);
seven_segment_decoder disp2(in2,seg2);
seven_segment_decoder disp3(in3,seg3);
seven_segment_decoder disp4(in4,seg4);

always @ (posedge clk) 
segclk <= segclk + 1'b1;

  always @ (posedge segclk or posedge clr)
begin
    if (clr == 1)
	begin
	    seg <= 7'b0000000;
	    an <= 4'b0000;
	    state <= LEFT;
	end
	
	else
	begin	   
	case (state)
	LEFT:
	   begin
	   seg <= seg1;
	   an <= 4'b0111;
	   state <= MIDLEFT;
	   end
	MIDLEFT:
	   begin
	   seg <= seg2;
	   an <= 4'b1011;
	   state <= MIDRIGHT;
	   end
	MIDRIGHT:
	   begin
	   seg <= seg3;
	   an <= 4'b1101;
	   state <= RIGHT;
	   end
	RIGHT:
	   begin
	   seg <= seg4;
	   an <= 4'b1110;
	   state <= LEFT;
	   end 
	endcase
	end
end

endmodule

Home Alarm System.srcs/sources_1/new/binarytoBCD.v
//////////////////////////////////////////////////////////////////////////////////
// This module is designed to convert a binary bumber to a BCD number.
// 
//////////////////////////////////////////////////////////////////////////////////
`timescale 1s / 1ms
module binarytoBCD(binary,thos,huns,tens,ones);

input [11:0] binary;
output reg [3:0] thos,huns,tens,ones;

reg [11:0] temp;

always @ (binary)
begin
    temp = binary;    
    thos = temp/1000;
    temp = temp%1000;
    huns = temp/100;
    temp = temp%100;
    tens = temp/10;
    temp = temp%10;
    ones = temp;    
end

endmodule

Home Alarm System.srcs/sources_1/new/home_alarm.v
//////////////////////////////////////////////////////////////////////////////////
// This is the main module describing the internal processing of
// our home alarm system.
//////////////////////////////////////////////////////////////////////////////////
`timescale 1s / 1ms
module home_alarm(clk,pass,act,door,win1,win2,win3,blinkled,alarmled,seg,an,buzzer);

input clk;
input [7:0] pass; //password
input act, door, win1, win2, win3;
output reg blinkled=0, alarmled=0;
output [6:0] seg;
output [3:0] an;
output reg buzzer=1;

localparam AOFF=2'b00, AON=2'b01, PASSCHECK=2'b10, SOUND=2'b11;
reg [1:0] state=AOFF;

integer passcounter=0;
localparam secondtime=1; //1 second
  reg [7:0] seconds=0;
parameter password=8'h55; // initial password
reg [3:0]active=4'b0000;

wire [3:0] thos,huns,tens,ones;

binarytoBCD bin({4'b0000,seconds},thos,huns,tens,ones);
seven_segment_driver seg7 (clk,1'b0,tens,ones,4'b0000,active,seg,an);

always @ (posedge clk)
case(state)
AOFF:	
	if (act == 1) state <= AON;
AON:
	if (door != 0) state <= PASSCHECK; //if door open, goto password check
	else if ((win1 | win2 | win3) != 0) state <= SOUND; //if windows open, goto sound state
PASSCHECK:  
	if (passcounter == secondtime) 
	begin
        seconds <= seconds  + 1'b1;
        blinkled <= ~blinkled;
        passcounter <= 0;
	end
	else if (pass == password)  //if correct password, alarm goto off state
	begin 
        blinkled <= 0;         
        seconds <= 0;           
        state <= AOFF;
	end
	else if (seconds == 8'b00010100) //if 20 seconds pass, goto sound state
	begin
        blinkled <= 0;
        seconds <= 0;                      
        state <= SOUND;
	end
	else 
	   passcounter <= passcounter + 1;
SOUND:
	if (pass == password) //if correct password, alarm off
	begin
        alarmled <= 0;
        state <= AOFF;
        buzzer <= 1;
	end
	else 
	begin
        alarmled <= 1;
        buzzer <= 0;  //start buzzer
	end
endcase

always @ (posedge clk)
case (state)
AOFF:
	active <= 4'b0000;
AON:
	active <= 4'b1010;
endcase

endmodule

Home Alarm System.srcs/sources_1/new/home_alarm_topmodule.v
`timescale 1s / 1ms
//////////////////////////////////////////////////////////////////////////////////
// College: Netaji Subhas University of Technology 
// Engineer: Yash Gupta 
// 
// Create Date: 16.05.2021 18:45:58
// Design Name: 
// Module Name: home_alarm_topmodule
// Project Name: Home alarm system
// Target Devices: Xilinx Artix 7 FPGA board
// Tool Versions: 
// Description: Verilog description of a home alarm system.
//              This is the top module of our project. It contains other modules and
//              make our Project work. We can also use sensors for internal security
//              in place of input from windows.
//
// Dependencies: 
// 
// Revision:
// Revision 0.01 - File Created
// Additional Comments:
// 
//////////////////////////////////////////////////////////////////////////////////


module home_alarm_topmodule(clk,sw,btnC,btnU,btnD,btnR,btnL,led,seg,an,JA);

input clk;
input [7:0] sw; //for password
input btnC, btnU; //C for activation & U represnts the door
input btnD,btnL,btnR; //windows
output [1:0] led;
output [6:0] seg;
output [3:0] an;
output [0:0] JA; //buzzer

//We don't need debouncing for simultion purpose, we would need it while implementing it on FPGA
//wire btnCclr,btnUclr,btnDclr,btnRclr,btnLclr;

//debounce dbnC(clk,btnC,btnCclr);
//debounce dbnU(clk,btnU,btnUclr);
//debounce dbnD(clk,btnD,btnDclr);
//debounce dbnL(clk,btnL,btnLclr);
//debounce dbnR(clk,btnR,btnRclr);

home_alarm Home_Alarm (clk,sw,btnC,btnU,btnD,btnR,btnL,led[1],led[0],seg,an,JA);



endmodule

Home Alarm System.srcs/sim_1/new/testbench.v
//////////////////////////////////////////////////////////////////////////////////
// This is the testbench for our Home alarm system project
// It is used fir simulations
//////////////////////////////////////////////////////////////////////////////////

`timescale 1s / 1ms

module home_alarm_topmodule_tb;
    
reg clk,btnC,btnD,btnL,btnR,btnU;
reg [7:0] sw;
wire [1:0] led;
wire [6:0] seg;
wire [3:0] an;
wire [0:0] JA;	

home_alarm_topmodule DUT (clk,sw,btnC,btnU,btnD,btnR,btnL,led,seg,an,JA);

initial begin
    clk = 0;
    forever
        #5 clk = ~clk;         
end

initial begin
    
    sw=8'b00000000;btnC=0;btnL=0;btnR=0;btnD=0;btnU=0;
    #10 btnC = 1;
    
//    //Testing Door
//    #10 btnU = 1;
//    #10 sw=8'b00001111;
//    #500 sw=8'b01010101;
//    //Working Coreectly
    
//    //Testing Windows  
    #10 btnL=1;
    #10 sw=8'b111111110;
    #50;
    #50 sw=8'b01010101;
//    //Working Correctly

    #100 $finish;
end

initial begin
  $display("\t\t\t\t time \tclk  sw  \tbtnC \tbtnU \tbtnD \tbtnR \tbtnL \tled \tseg \tan     \tJA");
  $monitor($time,"\t%b  %8b \t%b \t\t%b \t\t%b \t\t%b \t\t%b \t%b \t%7b \t%4b \t%b", clk,sw,btnC,btnU,btnD,btnR,btnL,led,seg,an,JA);
  $dumpfile("simulation_waveform.vcd");
  $dumpvars(0,home_alarm_topmodule_tb);
end
  
endmodule

Home Alarm System.sim/sim_1/behav/xsim/simulation_waveform.vcd
$date
   Tue May 18 16:25:39 2021
$end
$version
  2020.2
$end
$timescale
  1ps
$end
$scope module home_alarm_topmodule_tb $end
$var reg 1 ! clk $end
$var reg 1 " btnC $end
$var reg 1 # btnD $end
$var reg 1 $ btnL $end
$var reg 1 % btnR $end
$var reg 1 & btnU $end
$var reg 8 ' sw [7:0] $end
$var wire 2 ( led [1:0] $end
$var wire 7 ) seg [6:0] $end
$var wire 4 * an [3:0] $end
$var wire 1 + JA [0:0] $end
$scope module DUT $end
$var wire 1 , clk $end
$var wire 8 - sw [7:0] $end
$var wire 1 . btnC $end
$var wire 1 / btnU $end
$var wire 1 0 btnD $end
$var wire 1 1 btnL $end
$var wire 1 2 btnR $end
$var wire 2 ( led [1:0] $end
$var wire 7 ) seg [6:0] $end
$var wire 4 * an [3:0] $end
$var wire 1 + JA [0:0] $end
$scope module Home_Alarm $end
$var wire 1 , clk $end
$var wire 8 - pass [7:0] $end
$var wire 1 . act $end
$var wire 1 / door $end
$var wire 1 0 win1 $end
$var wire 1 2 win2 $end
$var wire 1 1 win3 $end
$var reg 1 3 blinkled $end
$var reg 1 4 alarmled $end
$var wire 7 ) seg [6:0] $end
$var wire 4 * an [3:0] $end
$var reg 1 5 buzzer $end
$var reg 2 6 state [1:0] $end
$var integer 32 7 passcounter $end
$var reg 8 8 seconds [7:0] $end
$var reg 4 9 active [3:0] $end
$var wire 4 : thos [3:0] $end
$var wire 4 ; huns [3:0] $end
$var wire 4 < tens [3:0] $end
$var wire 4 = ones [3:0] $end
$var parameter 2 > AOFF [1:0] $end
$var parameter 2 ? AON [1:0] $end
$var parameter 2 @ PASSCHECK [1:0] $end
$var parameter 2 A SOUND [1:0] $end
$var parameter 32 B secondtime [31:0] $end
$var parameter 8 C password [7:0] $end
$scope module bin $end
$var wire 12 D binary [11:0] $end
$var reg 4 E thos [3:0] $end
$var reg 4 F huns [3:0] $end
$var reg 4 G tens [3:0] $end
$var reg 4 H ones [3:0] $end
$var reg 12 I temp [11:0] $end
$upscope $end
$scope module seg7 $end
$var wire 1 , clk $end
$var wire 1 J clr $end
$var wire 4 < in1 [3:0] $end
$var wire 4 = in2 [3:0] $end
$var wire 4 K in3 [3:0] $end
$var wire 4 L in4 [3:0] $end
$var reg 7 M seg [6:0] $end
$var reg 4 N an [3:0] $end
$var wire 7 O seg1 [6:0] $end
$var wire 7 P seg2 [6:0] $end
$var wire 7 Q seg3 [6:0] $end
$var wire 7 R seg4 [6:0] $end
$var reg 13 S segclk [12:0] $end
$var reg 2 T state [1:0] $end
$var parameter 2 U LEFT [1:0] $end
$var parameter 2 V MIDLEFT [1:0] $end
$var parameter 2 W MIDRIGHT [1:0] $end
$var parameter 2 X RIGHT [1:0] $end
$scope module disp1 $end
$var wire 4 < in [3:0] $end
$var reg 7 Y out [6:0] $end
$upscope $end
$scope module disp2 $end
$var wire 4 = in [3:0] $end
$var reg 7 Z out [6:0] $end
$upscope $end
$scope module disp3 $end
$var wire 4 K in [3:0] $end
$var reg 7 [ out [6:0] $end
$upscope $end
$scope module disp4 $end
$var wire 4 L in [3:0] $end
$var reg 7 \ out [6:0] $end
$upscope $end
$upscope $end
$upscope $end
$upscope $end
$upscope $end
$enddefinitions $end
#0
$dumpvars
0!
0"
0#
0$
0%
0&
b0 '
b0 (
bx )
bx *
1+
0,
b0 -
0.
0/
00
01
02
03
04
15
b0 6
b0 7
b0 8
b0 9
b0 :
b0 ;
b0 <
b0 =
b0 >
b1 ?
b10 @
b11 A
b1 B
b1010101 C
b0 D
b0 E
b0 F
b0 G
b0 H
b0 I
0J
b0 K
b0 L
bx M
bx N
b1000000 O
b1000000 P
b1000000 Q
b1000000 R
b0 S
b0 T
b0 U
b1 V
b10 W
b11 X
b1000000 Y
b1000000 Z
b1000000 [
b1000000 \
$end
#5
1!
b1000000 )
b111 *
1,
b0 9
b1000000 M
b111 N
b1 S
b1 T
#10
0!
1"
0,
1.
#15
1!
1,
b1 6
b0 9
b10 S
#20
0!
1$
0,
11
#25
1!
b1011 *
1,
b11 6
b1010 9
b1010 L
b1011 N
b1000 R
b11 S
b10 T
b1000 \
#30
0!
b11111110 '
0,
b11111110 -
#35
1!
b1 (
0+
1,
14
05
b100 S
#40
0!
0,
#45
1!
b1101 *
1,
14
05
b1101 N
b101 S
b11 T
#50
0!
0,
#55
1!
1,
14
05
b110 S
#60
0!
0,
#65
1!
b1000 )
b1110 *
1,
14
05
b1000 M
b1110 N
b111 S
b0 T
#70
0!
0,
#75
1!
1,
14
05
b1000 S
#80
0!
0,
#85
1!
b1000000 )
b111 *
1,
14
05
b1000000 M
b111 N
b1001 S
b1 T
#90
0!
0,
#95
1!
1,
14
05
b1010 S
#100
0!
0,
#105
1!
b1011 *
1,
14
05
b1011 N
b1011 S
b10 T
#110
0!
0,
#115
1!
1,
14
05
b1100 S
#120
0!
0,
#125
1!
b1101 *
1,
14
05
b1101 N
b1101 S
b11 T
#130
0!
b1010101 '
0,
b1010101 -
#135
1!
b0 (
1+
1,
04
15
b0 6
b1110 S
#140
0!
0,
#145
1!
b1000 )
b1110 *
1,
b1 6
b0 9
b0 L
b1000 M
b1110 N
b1000000 R
b1111 S
b0 T
b1000000 \
#150
0!
0,
#155
1!
1,
b11 6
b1010 9
b1010 L
b1000 R
b10000 S
b1000 \
#160
0!
0,
#165
1!
b1000000 )
b111 *
1,
04
15
b0 6
b1000000 M
b111 N
b10001 S
b1 T
#170
0!
0,
#175
1!
1,
b1 6
b0 9
b0 L
b1000000 R
b10010 S
b1000000 \
#180
0!
0,
#185
1!
b1011 *
1,
b11 6
b1010 9
b1010 L
b1011 N
b1000 R
b10011 S
b10 T
b1000 \
#190
0!
0,
#195
1!
1,
04
15
b0 6
b10100 S
#200
0!
0,
#205
1!
b1101 *
1,
b1 6
b0 9
b0 L
b1101 N
b1000000 R
b10101 S
b11 T
b1000000 \
#210
0!
0,
#215
1!
1,
b11 6
b1010 9
b1010 L
b1000 R
b10110 S
b1000 \
#220
0!
0,
#225
1!
b1000 )
b1110 *
1,
04
15
b0 6
b1000 M
b1110 N
b10111 S
b0 T
